bccr_exchange_rates/__init__.py
bccr_exchange_rates/exceptions.py
bccr_exchange_rates/scraper.py
bccr_exchange_rates/utils.py
bccr_exchange_rates-1.0.0.dist-info/licenses/LICENSE
bccr_exchange_rates-1.0.0.dist-info/METADATA
bccr_exchange_rates-1.0.0.dist-info/WHEEL
bccr_exchange_rates-1.0.0.dist-info/top_level.txt
bccr_exchange_rates-1.0.0.dist-info/RECORD
