Metadata-Version: 2.4
Name: bccr-exchange-rates
Version: 1.0.0
Summary: Python library for scraping Costa Rican exchange rates from Banco Central de Costa Rica (BCCR)
Home-page: https://github.com/jloria13/bccr-exchange-rates
Author: Mauricio Loría
License: MIT
Project-URL: Homepage, https://github.com/yourusername/bccr-exchange-rates
Project-URL: Repository, https://github.com/yourusername/bccr-exchange-rates
Project-URL: Issues, https://github.com/yourusername/bccr-exchange-rates/issues
Project-URL: Documentation, https://github.com/yourusername/bccr-exchange-rates#readme
Keywords: bccr,costa rica,exchange rates,currency,scraping,banco central,tipo de cambio,compra y venta,tipo cambio
Classifier: Development Status :: 5 - Production/Stable
Classifier: Intended Audience :: Developers
Classifier: Intended Audience :: Financial and Insurance Industry
Classifier: License :: OSI Approved :: MIT License
Classifier: Programming Language :: Python :: 3
Classifier: Programming Language :: Python :: 3.11
Classifier: Programming Language :: Python :: 3.12
Classifier: Topic :: Office/Business :: Financial
Classifier: Topic :: Software Development :: Libraries :: Python Modules
Classifier: Operating System :: OS Independent
Requires-Python: >=3.11
License-File: LICENSE
Requires-Dist: requests>=2.31.0
Requires-Dist: beautifulsoup4>=4.12.0
Requires-Dist: python-dateutil>=2.8.0
Provides-Extra: dev
Requires-Dist: pytest>=8.0.0; extra == "dev"
Requires-Dist: pytest-cov>=4.0.0; extra == "dev"
Requires-Dist: black>=23.0.0; extra == "dev"
Requires-Dist: flake8>=6.0.0; extra == "dev"
Requires-Dist: mypy>=1.0.0; extra == "dev"
Dynamic: home-page
Dynamic: license-file
Dynamic: requires-python
